mcp_openai_websearch/__init__.py
mcp_openai_websearch/__main__.py
mcp_openai_websearch/server.py
mcp_openai_websearch-0.1.5.dist-info/METADATA
mcp_openai_websearch-0.1.5.dist-info/WHEEL
mcp_openai_websearch-0.1.5.dist-info/entry_points.txt
mcp_openai_websearch-0.1.5.dist-info/licenses/LICENSE
mcp_openai_websearch-0.1.5.dist-info/RECORD
