Metadata-Version: 2.4
Name: mcp-openai-websearch
Version: 0.1.5
Summary: using openai websearch as mcp server
License-File: LICENSE
Requires-Python: >=3.10
Requires-Dist: mcp==1.3.0
Requires-Dist: openai==1.66.2
Requires-Dist: pydantic-extra-types==2.10.3
Requires-Dist: pydantic==2.10.6
Requires-Dist: tzdata==2025.1
